trcli/__init__.py
trcli/cli.py
trcli/constants.py
trcli/settings.py
trcli/api/__init__.py
trcli/api/api_client.py
trcli/api/api_request_handler.py
trcli/api/api_response_verify.py
trcli/api/results_uploader.py
trcli/commands/__init__.py
trcli/commands/cmd_parse_junit.py
trcli/commands/cmd_parse_openapi.py
trcli/data_classes/__init__.py
trcli/data_classes/data_parsers.py
trcli/data_classes/dataclass_testrail.py
trcli/data_classes/validation_exception.py
trcli/data_providers/api_data_provider.py
trcli/readers/__init__.py
trcli/readers/file_parser.py
trcli/readers/junit_xml.py
trcli/readers/openapi_yml.py
trcli_a-1.5.1.dist-info/LICENSE.md
trcli_a-1.5.1.dist-info/METADATA
trcli_a-1.5.1.dist-info/WHEEL
trcli_a-1.5.1.dist-info/entry_points.txt
trcli_a-1.5.1.dist-info/top_level.txt
trcli_a-1.5.1.dist-info/RECORD
