Metadata-Version: 2.1
Name: trcli-a
Version: 1.5.1
License-File: LICENSE.md
Requires-Dist: click
Requires-Dist: pyyaml
Requires-Dist: junitparser
Requires-Dist: pyserde
Requires-Dist: requests
Requires-Dist: tqdm
Requires-Dist: humanfriendly
Requires-Dist: prance
Requires-Dist: openapi-spec-validator
